{
  "$schema": "https://raw.githubusercontent.com/spdx/spdx-spec/v2.2.1/schemas/spdx-schema.json",
  "spdxVersion": "SPDX-2.2",
  "dataLicense": "CC0-1.0",
  "SPDXID": "SPDXRef-DOCUMENT",
  "documentNamespace": "https://spdx.org/spdxdocs/boost-atomic-x64-linux-1.83.0-2f76cae2-e4de-4643-8433-0f9904185630",
  "name": "boost-atomic:x64-linux@1.83.0 e3eba265cd5a620f4d5b8b6ad84bc6ca83ae5c821aa67ee3219f6709be8b21a2",
  "creationInfo": {
    "creators": [
      "Tool: vcpkg-4c1df40a3c5c5e18de299a99e9accb03c2a82e1e"
    ],
    "created": "2024-07-12T09:38:34Z"
  },
  "relationships": [
    {
      "spdxElementId": "SPDXRef-port",
      "relationshipType": "GENERATES",
      "relatedSpdxElement": "SPDXRef-binary"
    },
    {
      "spdxElementId": "SPDXRef-port",
      "relationshipType": "CONTAINS",
      "relatedSpdxElement": "SPDXRef-file-0"
    },
    {
      "spdxElementId": "SPDXRef-port",
      "relationshipType": "CONTAINS",
      "relatedSpdxElement": "SPDXRef-file-1"
    },
    {
      "spdxElementId": "SPDXRef-binary",
      "relationshipType": "GENERATED_FROM",
      "relatedSpdxElement": "SPDXRef-port"
    },
    {
      "spdxElementId": "SPDXRef-file-0",
      "relationshipType": "CONTAINED_BY",
      "relatedSpdxElement": "SPDXRef-port"
    },
    {
      "spdxElementId": "SPDXRef-file-1",
      "relationshipType": "CONTAINED_BY",
      "relatedSpdxElement": "SPDXRef-port"
    }
  ],
  "packages": [
    {
      "name": "boost-atomic",
      "SPDXID": "SPDXRef-port",
      "versionInfo": "1.83.0",
      "downloadLocation": "NOASSERTION",
      "homepage": "https://github.com/boostorg/atomic",
      "licenseConcluded": "BSL-1.0",
      "licenseDeclared": "NOASSERTION",
      "copyrightText": "NOASSERTION",
      "description": "Boost atomic module",
      "comment": "This is the port (recipe) consumed by vcpkg."
    },
    {
      "name": "boost-atomic:x64-linux",
      "SPDXID": "SPDXRef-binary",
      "versionInfo": "e3eba265cd5a620f4d5b8b6ad84bc6ca83ae5c821aa67ee3219f6709be8b21a2",
      "downloadLocation": "NONE",
      "licenseConcluded": "BSL-1.0",
      "licenseDeclared": "NOASSERTION",
      "copyrightText": "NOASSERTION",
      "comment": "This is a binary package built by vcpkg."
    },
    {
      "SPDXID": "SPDXRef-resource-1",
      "name": "boostorg/atomic",
      "downloadLocation": "git+https://github.com/boostorg/atomic@boost-1.83.0",
      "licenseConcluded": "NOASSERTION",
      "licenseDeclared": "NOASSERTION",
      "copyrightText": "NOASSERTION",
      "checksums": [
        {
          "algorithm": "SHA512",
          "checksumValue": "d6ee15758d9de6c64e9bb307e3b9a5a9aea6d4555be2df78c8ed8089d9da75926f6ec376c2917fbb8c2f985f23b0b926b39fb2d02921c443a83edb77e0455996"
        }
      ]
    }
  ],
  "files": [
    {
      "fileName": ".//home/arkadiusz/Projects/OmniView/vcpkg/ports/boost-atomic/vcpkg.json",
      "SPDXID": "SPDXRef-file-0",
      "checksums": [
        {
          "algorithm": "SHA256",
          "checksumValue": "49280b5cb3227edd32e3bb515297d48a4da3488571d8eccd24bf3c21d4eb965e"
        }
      ],
      "licenseConcluded": "NOASSERTION",
      "copyrightText": "NOASSERTION"
    },
    {
      "fileName": ".//home/arkadiusz/Projects/OmniView/vcpkg/ports/boost-atomic/portfile.cmake",
      "SPDXID": "SPDXRef-file-1",
      "checksums": [
        {
          "algorithm": "SHA256",
          "checksumValue": "4ca4b7c1b08f1d5aafbd6a0d3494ddda2af82ec47a8966dd52cddbeb51a3d244"
        }
      ],
      "licenseConcluded": "NOASSERTION",
      "copyrightText": "NOASSERTION"
    }
  ]
}
